{"assets/dotenv":["assets/dotenv"],"assets/images/cloud.png":["assets/images/cloud.png"],"assets/images/max temp.png":["assets/images/max temp.png"],"assets/images/max_temp.png":["assets/images/max_temp.png"],"assets/images/min_temp.png":["assets/images/min_temp.png"],"assets/images/night.png":["assets/images/night.png"],"assets/images/rain.png":["assets/images/rain.png"],"assets/images/rainy.png":["assets/images/rainy.png"],"assets/images/snow.png":["assets/images/snow.png"],"assets/images/sun.png":["assets/images/sun.png"],"assets/images/sunny.png":["assets/images/sunny.png"],"assets/images/sunny_cloud.png":["assets/images/sunny_cloud.png"],"assets/images/thunder.png":["assets/images/thunder.png"],"assets/images/wind.png":["assets/images/wind.png"],"packages/cupertino_icons/assets/CupertinoIcons.ttf":["packages/cupertino_icons/assets/CupertinoIcons.ttf"]}